bifrost_common_py/DataFrame.py
bifrost_common_py/Log.py
bifrost_common_py/SelectFrom.py
bifrost_common_py/__init__.py
bifrost_common_py/idOfRef.py
bifrost_common_py/safepointer.py
bifrost_common_py/selectors.py
bifrost_common_py/time.py
bifrost_common_py/tokens.py
bifrost_common_py-0.8.dist-info/METADATA
bifrost_common_py-0.8.dist-info/WHEEL
bifrost_common_py-0.8.dist-info/top_level.txt
bifrost_common_py-0.8.dist-info/RECORD
