Metadata-Version: 2.1
Name: bifrost-common-py
Version: 0.8
Summary: Common python library functions for interacting with BIFROST.
Home-page: https://bifrost.siemens.com/en
Download-URL: 
Author: Manuel Matzinger
Author-email: bifrost.at@siemens.com
Keywords: bifrost,bifrost-common
